napari_clusters_plotter/__init__.py
napari_clusters_plotter/_algorithm_widget.py
napari_clusters_plotter/_algorithms.py
napari_clusters_plotter/_dim_reduction_and_clustering.py
napari_clusters_plotter/_new_plotter_widget.py
napari_clusters_plotter/_sample_data.py
napari_clusters_plotter/_utilities.py
napari_clusters_plotter/_version.py
napari_clusters_plotter/napari.yaml
napari_clusters_plotter/plotter_inputs.ui
napari_clusters_plotter/_tests/__init__.py
napari_clusters_plotter/_tests/test_dimensionality_reduction.py
napari_clusters_plotter/_tests/test_layers.py
napari_clusters_plotter/_tests/test_plotter.py
napari_clusters_plotter/_tests/test_sample_data.py
napari_clusters_plotter/sample_data/BBBC007_v1_images/data_source.txt
napari_clusters_plotter/sample_data/BBBC007_v1_images/A9/A9 p10d.tif
napari_clusters_plotter/sample_data/BBBC007_v1_images/A9/A9 p10d_features.csv
napari_clusters_plotter/sample_data/BBBC007_v1_images/A9/A9 p10d_labels.tif
napari_clusters_plotter/sample_data/BBBC007_v1_images/A9/A9 p5d.tif
napari_clusters_plotter/sample_data/BBBC007_v1_images/A9/A9 p5d_features.csv
napari_clusters_plotter/sample_data/BBBC007_v1_images/A9/A9 p5d_labels.tif
napari_clusters_plotter/sample_data/BBBC007_v1_images/A9/A9 p7d.tif
napari_clusters_plotter/sample_data/BBBC007_v1_images/A9/A9 p7d_features.csv
napari_clusters_plotter/sample_data/BBBC007_v1_images/A9/A9 p7d_labels.tif
napari_clusters_plotter/sample_data/BBBC007_v1_images/A9/A9 p9d.tif
napari_clusters_plotter/sample_data/BBBC007_v1_images/A9/A9 p9d_features.csv
napari_clusters_plotter/sample_data/BBBC007_v1_images/A9/A9 p9d_labels.tif
napari_clusters_plotter/sample_data/BBBC007_v1_images/f96 (17)/17P1_POS0006_D_1UL.tif
napari_clusters_plotter/sample_data/BBBC007_v1_images/f96 (17)/17P1_POS0006_D_1UL_features.csv
napari_clusters_plotter/sample_data/BBBC007_v1_images/f96 (17)/17P1_POS0006_D_1UL_labels.tif
napari_clusters_plotter/sample_data/BBBC007_v1_images/f96 (17)/17P1_POS0007_D_1UL.tif
napari_clusters_plotter-0.10.0.dist-info/licenses/LICENSE
napari_clusters_plotter-0.10.0.dist-info/METADATA
napari_clusters_plotter-0.10.0.dist-info/WHEEL
napari_clusters_plotter-0.10.0.dist-info/entry_points.txt
napari_clusters_plotter-0.10.0.dist-info/top_level.txt
napari_clusters_plotter-0.10.0.dist-info/RECORD
