Metadata-Version: 2.4
Name: napari-clusters-plotter
Version: 0.10.0
Summary: A plugin to use with napari for clustering objects according to their properties
Author: Laura Zigutyte, Ryan Savill, Marcelo Zoccoler, Thorsten Wagner, Robert Haase
Author-email: Johannes Soltwedel <johannes_richard.soltwedel@tu-dresden.de>
License: Copyright (c) 2022, DFG Cluster of Excellence "Physics of Life" TU Dresden: Robert Haase, Laura Zigutyte, Marcello Zoccoler, Ryan Savill, Johannes Müller and Max Planck Institute of Molecular Physiology Dortmund: Thorsten Wagner
Project-URL: Bug Tracker, https://github.com/BiAPoL/napari-clusters-plotter/issues
Project-URL: Documentation, https://github.com/BiAPoL/napari-clusters-plotter
Project-URL: Source Code, https://github.com/BiAPoL/napari-clusters-plotter
Project-URL: User Support, https://github.com/BiAPoL/napari-clusters-plotter/issues
Classifier: Development Status :: 2 - Pre-Alpha
Classifier: Framework :: napari
Classifier: Intended Audience :: Developers
Classifier: License :: OSI Approved :: BSD License
Classifier: Operating System :: OS Independent
Classifier: Programming Language :: Python
Classifier: Programming Language :: Python :: 3
Classifier: Programming Language :: Python :: 3 :: Only
Classifier: Programming Language :: Python :: 3.10
Classifier: Programming Language :: Python :: 3.11
Classifier: Programming Language :: Python :: 3.12
Classifier: Programming Language :: Python :: 3.13
Classifier: Topic :: Scientific/Engineering :: Image Processing
Requires-Python: >=3.9
License-File: LICENSE
Requires-Dist: numpy
Requires-Dist: magicgui
Requires-Dist: qtpy
Requires-Dist: napari
Requires-Dist: npe2
Requires-Dist: scikit-learn
Requires-Dist: pandas
Requires-Dist: umap-learn
Requires-Dist: scikit-image
Requires-Dist: scipy
Requires-Dist: biaplotter>=0.3.1
Requires-Dist: imagecodecs
Provides-Extra: testing
Requires-Dist: tox; extra == "testing"
Requires-Dist: pytest; extra == "testing"
Requires-Dist: pytest-cov; extra == "testing"
Requires-Dist: pytest-qt; extra == "testing"
Requires-Dist: napari; extra == "testing"
Requires-Dist: pyqt5; extra == "testing"
Dynamic: license-file
